{"appelations": ["Adjoint / Adjointe au chef de rayon produits non alimentaires", "Adjoint / Adjointe au responsable de rayon produits non alimentaires", "Chef de rayon bazar", "Chef de rayon bricolage", "Chef de rayon \u00e9lectrom\u00e9nager", "Chef de rayon \u00e9quipement de la maison", "Chef de rayon \u00e9quipement de la personne", "Chef de rayon hygi\u00e8ne et parfumerie", "Chef de rayon informatique", "Chef de rayon jardinerie et animalerie", "Chef de rayon jouets", "Chef de rayon librairie papeterie", "Chef de rayon photo image et son", "Chef de rayon produits culturels", "Chef de rayon produits non alimentaires", "Chef de rayon pu\u00e9riculture", "Chef de rayon sport", "Chef de rayon t\u00e9l\u00e9phonie", "Chef de rayon textile", "Manager de rayon produits non alimentaires", "Responsable de rayon produits non alimentaires"], "description": ["Supervise les flux de ventes, met en place les op\u00e9rations commerciales et coordonne les activit\u00e9s d'une \u00e9quipe de vendeurs et d'employ\u00e9s de libre-service d'un ou plusieurs rayon(s) de produits non alimentaires (bricolage, produits culturels, \u00e9lectrom\u00e9nager, informatique, \u00e9quipement de la personne, ...) selon la r\u00e9glementation du commerce et la strat\u00e9gie commerciale de l'enseigne.", "Peut conseiller la client\u00e8le sur les produits en rayon."], "expertises": ["Suivre l'\u00e9tat des stocks", "Pr\u00e9parer les commandes", "D\u00e9finir des besoins en approvisionnement", "V\u00e9rifier la conformit\u00e9 de la livraison", "Superviser le stockage des produits", "Contr\u00f4ler la conformit\u00e9 d'un produit", "Contr\u00f4ler la mise en rayon des articles", "Adapter le plan d'implantation des articles", "Analyser les r\u00e9sultats des ventes", "D\u00e9terminer des mesures correctives", "Concevoir les op\u00e9rations commerciales selon les marges, le chiffre d'affaires et les pr\u00e9visions", "D\u00e9coder un tableau de bord", "Coordonner l'activit\u00e9 d'une \u00e9quipe"], "competences": ["Gestes et postures de manutention", "Merchandising / Marchandisage", "Statistiques", "Logiciels de gestion de stocks", "E-procurement", "Outils bureautiques", "Gestion des stocks et des approvisionnements", "Utilisation de cadencier"], "expertises_extra": ["R\u00e9ceptionner des retours clients", "Identifier des invendus", "Effectuer des retours fournisseurs", "Effectuer des remboursements", "Effectuer des \u00e9changes de produits", "N\u00e9gocier un contrat", "N\u00e9gocier des prix", "Organiser l'inventaire des produits d'un magasin", "Effectuer des relev\u00e9s de prix aupr\u00e8s de la concurrence", "Recruter du personnel", "Former du personnel \u00e0 des proc\u00e9dures et techniques", "Organiser des actions de formation"], "competences_extra": ["Techniques commerciales", "Techniques d'inventaire", "Veille concurrentielle", "Utilisation d'appareils de lecture optique de codes-barres (pistolet, flasheur, ...)", "Gestion des Ressources Humaines", "Techniques p\u00e9dagogiques"]}