{"appelations": ["Accueillant familial / Accueillante familiale aupr\u00e8s d'enfants", "Accueillant familial / Accueillante familiale th\u00e9rapeutique aupr\u00e8s d'enfants", "Agent sp\u00e9cialis\u00e9 / Agente sp\u00e9cialis\u00e9e des \u00e9coles maternelles -ASEM-", "Agent sp\u00e9cialis\u00e9 / Agente sp\u00e9cialis\u00e9e des \u00e9coles primaires", "Aide maternel / maternelle d'\u00e9cole", "Aide maternel / maternelle de cr\u00e8che - halte-garderie", "Assistant / Assistante accueil petite enfance", "Assistant familial / Assistante familiale", "Assistant maternel / Assistante maternelle", "Assistant maternel / Assistante maternelle \u00e0 domicile", "Assistant maternel / Assistante maternelle du particulier employeur", "Assistant maternel / Assistante maternelle en famille d'accueil", "Assistant maternel agr\u00e9\u00e9 / Assistante maternelle agr\u00e9\u00e9e", "Auxiliaire de vie sociale aupr\u00e8s d'enfants", "Auxiliaire parental / parentale", "Baby-sitter", "\u00c9ducateur familial / \u00c9ducatrice familiale", "Employ\u00e9 / Employ\u00e9e au pair", "Employ\u00e9 familial / Employ\u00e9e familiale aupr\u00e8s d'enfants", "Garde d'enfant \u00e0 domicile", "Gouvernant / Gouvernante d'enfant \u00e0 domicile", "Ma\u00eetre / Ma\u00eetresse de maison d'enfants", "Nourrice"], "description": ["Aide les enfants dans la r\u00e9alisation des actes de la vie quotidienne (habillage, prise de repas...).", "M\u00e8ne avec eux des activit\u00e9s d'\u00e9veil (jeux, apprentissage de la vie collective...).", "Peut effectuer l'entretien du cadre de vie des enfants."], "expertises": ["Pr\u00e9parer et donner un repas, une boisson \u00e0 l'enfant", "Entretenir les espaces de vie et le linge de l'enfant", "Proc\u00e9der \u00e0 la toilette et aux soins de l'enfant", "Procurer \u00e0 l'enfant des \u00e9l\u00e9ments de confort, de r\u00e9confort (bercement, doudou, ...)", "Accompagner l'enfant dans l'apprentissage des gestes de la vie quotidienne et des r\u00e8gles de vie en collectivit\u00e9", "Animer les activit\u00e9s ludiques ou aider l'enfant lors d'activit\u00e9s d'\u00e9veil et d'apprentissage", "Observer le comportement et l'\u00e9volution de l'enfant et informer parents, familles, enseignants"], "competences": ["Techniques d'\u00e9veil de l'enfant", "Di\u00e9t\u00e9tique", "Psychologie de l'enfant", "Pathologies de l'enfant", "Produits de nettoyage", "Caract\u00e9ristiques des produits d'entretien", "R\u00e8gles de s\u00e9curit\u00e9 domestique", "Gestes d'urgence et de secours", "Relation \u00e0 l'enfant ou l'adolescent", "R\u00e8gles d'hygi\u00e8ne et de propret\u00e9"], "expertises_extra": ["Intervenir aupr\u00e8s de nourrissons", "Intervenir aupr\u00e8s d'enfants de 3 \u00e0 6 ans", "Intervenir aupr\u00e8s d'enfants de 6 \u00e0 10 ans", "Intervenir aupr\u00e8s d'enfants de + de 10 ans", "Intervenir aupr\u00e8s d'enfants malades", "Intervenir aupr\u00e8s d'enfants maltrait\u00e9s", "Intervenir aupr\u00e8s d'enfants en situation de handicap", "Distribuer ou administrer des m\u00e9dicaments \u00e0 un enfant selon une prescription m\u00e9dicale", "Accueillir l'enfant et le guider \u00e0 son arriv\u00e9e dans la structure", "Surveiller le d\u00e9roulement des devoirs d'un enfant scolaris\u00e9 ou apporter une aide", "Pratiquer des exercices pour un enfant d\u00e9ficient selon un protocole th\u00e9rapeutique", "Collaborer avec l'ensemble des intervenants \u00e0 la r\u00e9alisation d'un objectif commun", "Actualiser la documentation professionnelle et r\u00e9glementaire", "Renseigner les documents de suivi d'une personne"], "competences_extra": ["Caract\u00e9ristiques socio-culturelles des publics", "Outils bureautiques"]}